common_stats/__init__.py
common_stats/statistics.py
tests/__init__.py
tests/test_statistics.py
common_stats-0.0.2.dist-info/LICENSE.txt
common_stats-0.0.2.dist-info/METADATA
common_stats-0.0.2.dist-info/WHEEL
common_stats-0.0.2.dist-info/top_level.txt
common_stats-0.0.2.dist-info/RECORD
